streamlit_cropperjs/__init__.py
streamlit_cropperjs/frontend/build/asset-manifest.json
streamlit_cropperjs/frontend/build/bootstrap.min.css
streamlit_cropperjs/frontend/build/index.html
streamlit_cropperjs/frontend/build/static/js/main.3d3d1fc2.js
streamlit_cropperjs/frontend/build/static/js/main.3d3d1fc2.js.LICENSE.txt
streamlit_cropperjs/frontend/build/static/js/main.3d3d1fc2.js.map
streamlit_cropperjs-0.0.9.dist-info/LICENSE
streamlit_cropperjs-0.0.9.dist-info/METADATA
streamlit_cropperjs-0.0.9.dist-info/WHEEL
streamlit_cropperjs-0.0.9.dist-info/top_level.txt
streamlit_cropperjs-0.0.9.dist-info/RECORD
