Metadata-Version: 2.1
Name: streamlit-cropperjs
Version: 0.0.9
Summary: A streamlit module integrating cropperjs
Home-page: https://github.com/erjieyong/streamlit-cropperjs
Author: erjieyong
Author-email: erjieyong@gmail.com
License: UNKNOWN
Platform: UNKNOWN
Requires-Python: >=3.6
Requires-Dist: streamlit (>=0.63)
